{
  "category": [
    {
      "任天堂": {
        "hardware_name": {
          "ファミリーコンピュータ": {
            "where_to_save": "カセット",
            "how_to_save": "レトロフリーク経由でバックアップ"
          },
          "スーパーファミコン": {
            "where_to_save": "カセット",
            "how_to_save": "レトロフリーク経由でバックアップ"
          },
          "バーチャルボーイ": {
            "where_to_save": "カセット",
            "how_to_save": "※調査
          },
          "NINTENDO64": {
            "where_to_save": "カセット",
            "how_to_save": "レトロフリーク経由でバックアップ"
          },
          "ニンテンドーゲームキューブ": {
            "where_to_save": "メモリーカード",
            "how_to_save": "Wii経由でバックアップ"
          },
          "Wii": {
            "where_to_save": "本体ストレージ",
            "how_to_save": "本体経由でバックアップ"
          },
          "WiiU": {
            "where_to_save": "本体ストレージ",
            "how_to_save": "本体経由でバックアップ"
          },
          "NintendoSwitch": {
            "where_to_save": "本体ストレージ",
            "how_to_save": "※調査"
          },
          "ゲームボーイ": {
            "where_to_save": "カセット",
            "how_to_save": "レトロフリーク経由でバックアップ"
          },
          "ゲームボーイカラー": {
            "where_to_save": "カセット",
            "how_to_save": "レトロフリーク経由でバックアップ"
          },
          "ゲームボーイアドバンス": {
            "where_to_save": "カセット",
            "how_to_save": "レトロフリーク経由でバックアップ"
          },
          "ニンテンドーDS": {
            "where_to_save": "カセット",
            "how_to_save": "※調査"
          },
          "ニンテンドー3DS": {
            "where_to_save": "カセット",
            "how_to_save": "※調査"
          }
        }
      },
      "SNK": {
        "hardware_name": {
          "Multi Video System": {
            "where_to_save": "カセット",
            "how_to_save": "※調査"
          },
          "NEOGEO": {
            "where_to_save": "メモリーカード",
            "how_to_save": "※調査"
          },
          "ネオジオCD": {
            "where_to_save": "メモリーカード",
            "how_to_save": "※調査"
          },
          "ネオジオポケット": {
            "where_to_save": "カセット",
            "how_to_save": "※調査"
          },
          "ネオジオポケットカラー": {
            "where_to_save": "カセット",
            "how_to_save": "※調査"
          }
        }
      },
      "NEC": {
        "hardware_name": {
          "PCエンジン": {
            "where_to_save": "カセット",
            "how_to_save": "レトロフリーク経由でバックアップ"
          },
          "PC-FX": {
            "where_to_save": "本体ストレージ、メモリーカード",
            "how_to_save": "※調査"
          }
        }
      },
      "エポック": {
        "hardware_name": {
          "カセットビジョン": {
            "where_to_save": "セーブ機能なし",
            "how_to_save": "-"
          },
          "スーパーカセットビジョン": {
            "where_to_save": "セーブ機能なし",
            "how_to_save": "-"
          }
        }
      }
    },
      "Microsoft": {
        "hardware_name": {
          "Xbox": {
            "where_to_save": "本体ストレージ",
            "how_to_save": "※調査"
          },
          "Xbox360": {
            "where_to_save": "本体ストレージ",
            "how_to_save": "※調査"
          },
          "XboxOne": {
            "where_to_save": "本体ストレージ",
            "how_to_save": "※調査"
          },
          "XboxSeriesX/S": {
            "where_to_save": "本体ストレージ",
            "how_to_save": "※調査"
          }
        }
      }
    },
      "BANDAI": {
        "hardware_name": {
          "プレイディア": {
            "where_to_save": "セーブ機能なし",
            "how_to_save": "-"
          },
          "ピピンアットマーク": {
            "where_to_save": "メモリーカード",
            "how_to_save": "※調査"
          },
          "ワンダースワン": {
            "where_to_save": "カセット",
            "how_to_save": "※調査"
          },
          "ワンダースワンカラー": {
            "where_to_save": "カセット",
            "how_to_save": "※調査"
          }
        }
      }
    },
      "SEGA": {
        "hardware_name": {
          "SG-1000": {
            "where_to_save": "カセット",
            "how_to_save": "レトロフリーク経由でバックアップ"
          },
          "セガ・マークⅢ": {
            "where_to_save": "カセット",
            "how_to_save": "レトロフリーク経由でバックアップ"
          },
          "メガドライブ": {
            "where_to_save": "カセット",
            "how_to_save": "レトロフリーク経由でバックアップ"
          },
          "メガCD": {
            "where_to_save": "メモリーカード",
            "how_to_save": "※調査"
          },
          "スーパー32X": {
            "where_to_save": "カセット",
            "how_to_save": "※調査"
          },
          "セガサターン": {
            "where_to_save": "メモリーカード",
            "how_to_save": "※調査"
          },
          "ドリームキャスト": {
            "where_to_save": "メモリーカード",
            "how_to_save": "※調査"
          },
          "ゲームギア": {
            "where_to_save": "カセット",
            "how_to_save": "レトロフリーク経由でバックアップ"
          }
        }
      }
    },
      "SIE": {
        "hardware_name": {
          "PlayStation1": {
            "where_to_save": "メモリーカード",
            "how_to_save": "本体からメモカブートを使用してSDカード経由でバックアップ"
          },
          "PlayStation2": {
            "where_to_save": "メモリーカード",
            "how_to_save": "本体からメモカブートを使用してSDカード経由でバックアップ"
          },
          "PlayStation3": {
            "where_to_save": "本体ストレージ",
            "how_to_save": "※調査"
          },
          "PlayStation4": {
            "where_to_save": "本体ストレージ",
            "how_to_save": "※調査"
          },
          "PlayStation5": {
            "where_to_save": "本体ストレージ",
            "how_to_save": "※調査"
          },
          "PlayStationPortable": {
            "where_to_save": "メモリースティック",
            "how_to_save": "本体経由でバックアップ"
          },
          "PlayStationVita": {
            "where_to_save": "メモリースティック",
            "how_to_save": "本体経由でバックアップ"
          }
        }
      }
    },
      "Panasonic": {
        "hardware_name": {
          "3DO": {
            "where_to_save": "本体ストレージ",
            "how_to_save": "-"
          }
        }
      }
    },
      "CASIO": {
        "hardware_name": {
          "LOOPY": {
            "where_to_save": "セーブ機能なし",
            "how_to_save": "-"
          }
        }
      }
    },
      "ASCII": {
        "hardware_name": {
          "MSX1": {
            "where_to_save": "カセット",
            "how_to_save": "※調査"
          },
          "MSX2": {
            "where_to_save": "カセット",
            "how_to_save": "※調査"
          },
          "MSX2+": {
            "where_to_save": "カセット",
            "how_to_save": "※調査"
          },
          "MSXturboR": {
            "where_to_save": "カセット",
            "how_to_save": "※調査"
          }
        }
      }
    },
      "Tomy": {
        "hardware_name": {
          "ぴゅう太": {
            "where_to_save": "セーブ機能なし",
            "how_to_save": "-"
          }
        }
      }
    }
  ]
}
